MANIFEST.in
README.md
setup.cfg
setup.py
disklist/__init__.py
disklist/disklist.py
disklist.egg-info/PKG-INFO
disklist.egg-info/SOURCES.txt
disklist.egg-info/dependency_links.txt
disklist.egg-info/top_level.txt