Metadata-Version: 1.1
Name: disklist
Version: 0.4.0
Summary: A list implementation that use a tempfile as its backend.
Home-page: https://github.com/Belval/disklist
Author: Edouard Belval
Author-email: edouard@belval.org
License: MIT
Keywords: list disk disklist
Platform: UNKNOWN
Classifier: Development Status :: 3 - Alpha
Classifier: Intended Audience :: Developers
Classifier: License :: OSI Approved :: MIT License
Classifier: Programming Language :: Python :: 3
Classifier: Programming Language :: Python :: 3.3
Classifier: Programming Language :: Python :: 3.4
Classifier: Programming Language :: Python :: 3.5
Classifier: Programming Language :: Python :: 3.6
